README.md
setup.py
websiteblocker/__init__.py
websiteblocker/web.py
websiteblocker.egg-info/PKG-INFO
websiteblocker.egg-info/SOURCES.txt
websiteblocker.egg-info/dependency_links.txt
websiteblocker.egg-info/entry_points.txt
websiteblocker.egg-info/top_level.txt